{"modelclass":{"value":"open20\\amos\\events\\models\\EventAccreditationList","name":"modelClass"},"searchmodelclass":{"value":"open20\\amos\\events\\models\\search\\EventAccreditationListSearch","name":"searchModelClass"},"controllerclass":{"value":"open20\\amos\\events\\controllers\\EventAccreditationListController","name":"controllerClass"},"basecontrollerclass":{"value":"open20\\amos\\core\\controllers\\CrudController","name":"baseControllerClass"},"viewpath":{"value":"@vendor\/open20\/amos-events\/src\/views","name":"viewPath"},"pathprefix":{"value":"","name":"pathPrefix"},"enablei18n":{"value":"1","name":"enableI18N"},"singularentities":{"value":false,"name":"singularEntities"},"indexwidgettype":{"value":"grid","name":"indexWidgetType"},"formlayout":{"value":"horizontal","name":"formLayout"},"actionbuttonclass":{"value":"yii\\grid\\ActionColumn","name":"actionButtonClass"},"providerlist":{"value":["open20\\amos\\core\\giiamos\\crud\\providers\\EditorProvider","open20\\amos\\core\\giiamos\\crud\\providers\\DateTimeProvider","open20\\amos\\core\\giiamos\\crud\\providers\\DateProvider","open20\\amos\\core\\giiamos\\crud\\providers\\EditableProvider","open20\\amos\\core\\giiamos\\crud\\providers\\RelationProvider","open20\\amos\\core\\giiamos\\crud\\providers\\CallbackProvider","open20\\amos\\core\\giiamos\\crud\\providers\\OptsProvider"],"name":"providerList"},"template":{"value":"advanced","name":"template"},"accessfilter":{"value":false,"name":"accessFilter"},"modelmessagecategory":{"value":"models","name":"modelMessageCategory"}}